pyelectroluxgroup/__init__.py
pyelectroluxgroup/api.py
pyelectroluxgroup/appliance.py
pyelectroluxgroup/auth.py
pyelectroluxgroup/map.py
pyelectroluxgroup/token_manager.py
pyelectroluxgroup/token_managers/filesystem.py
pyelectroluxgroup-0.2.3.dist-info/LICENSE
pyelectroluxgroup-0.2.3.dist-info/METADATA
pyelectroluxgroup-0.2.3.dist-info/WHEEL
pyelectroluxgroup-0.2.3.dist-info/RECORD
