Metadata-Version: 2.3
Name: pyelectroluxgroup
Version: 0.2.3
Summary: This is a Python client for the Electrolux Group API. It is a simple wrapper around the API.
Author: Johan Nenzén
Author-email: johan.nanzen@gmail.com
Requires-Python: >=3.10
Classifier: Programming Language :: Python :: 3
Classifier: Programming Language :: Python :: 3.10
Classifier: Programming Language :: Python :: 3.11
Classifier: Programming Language :: Python :: 3.12
Classifier: Programming Language :: Python :: 3.13
Provides-Extra: cli
Requires-Dist: aiohttp (>=3.9.5,<4.0.0)
Requires-Dist: pyjwt (>=2.8.0,<3.0.0)
Project-URL: Repository, https://github.com/JohNan/pyelectroluxgroup
